partio.libs/libz-745e0a09.so.1.2.7
partio-1.0.0.dist-info/LICENSE
partio-1.0.0.dist-info/WHEEL
partio-1.0.0.dist-info/RECORD
partio-1.0.0.dist-info/METADATA
partio-1.0.0.dist-info/top_level.txt
partio/partio.py
partio/libpartio.so.1
partio/__init__.py
partio/_partio.so
