Metadata-Version: 2.1
Name: partio
Version: 1.0.0
Summary: A Python wrapper for partio
Home-page: UNKNOWN
License: UNKNOWN
Platform: UNKNOWN
Requires-Python: >=3.4
License-File: LICENSE
